opsdnpy/__init__.py
opsdnpy/app.py
opsdnpy/app_manager.py
opsdnpy/basic_app.py
opsdnpy/controller.py
opsdnpy/data_path.py
opsdnpy/op_timer.py
opsdnpy-0.2.1.dist-info/METADATA
opsdnpy-0.2.1.dist-info/WHEEL
opsdnpy-0.2.1.dist-info/top_level.txt
opsdnpy-0.2.1.dist-info/RECORD
