Metadata-Version: 2.1
Name: opsdnpy
Version: 0.2.1
Summary: A python package for OPSDN
Home-page: https://github.com/ZacharyJia/opsdn
Author: Jia Zequn
Author-email: zachary@bjtu.edu.cn
License: Apache 2.0
Platform: UNKNOWN
Classifier: Programming Language :: Python :: 3
Classifier: Operating System :: OS Independent
Requires-Dist: ryu (==4.34)
Requires-Dist: networkx (==2.8.2)
